{
  "$schema": "https://ui.shadcn.com/schema/registry-item.json",
  "name": "analytics-workspace",
  "type": "registry:workspace",
  "title": "Agent-Native Analytics Workspace",
  "description": "Agent-Native Analytics Agent-Native template ported into Studio UI as a Harness-safe workspace surface with route inventory, provenance, resident-renderer blocks, and display-only agent/action affordances.",
  "dependencies": [
    "@jami-studio/ui"
  ],
  "registryDependencies": [
    "jami-theme",
    "panel",
    "button",
    "chart",
    "agent-panel",
    "analytics-app",
    "analytics-catchall-page",
    "analytics-home-page",
    "analytics-adhoc-detail-page",
    "analytics-analyses-detail-page",
    "analytics-analyses-index-page",
    "analytics-ask-page",
    "analytics-catalog-page",
    "analytics-chart-page",
    "analytics-dashboard-page",
    "analytics-dashboards-detail-page",
    "analytics-dashboards-index-page",
    "analytics-data-dictionary-page",
    "analytics-data-sources-page",
    "analytics-extensions-detail-detail-page",
    "analytics-extensions-detail-page",
    "analytics-extensions-index-page",
    "analytics-extensions-page",
    "analytics-overview-page",
    "analytics-sessions-detail-page",
    "analytics-sessions-index-page",
    "analytics-settings-page",
    "analytics-team-page",
    "analytics-traffic-dashboard-page",
    "analytics-traffic-page",
    "analytics-catchall-block",
    "analytics-home-block",
    "analytics-adhoc-detail-block",
    "analytics-analyses-detail-block",
    "analytics-analyses-index-block",
    "analytics-ask-block",
    "analytics-catalog-block",
    "analytics-chart-block",
    "analytics-dashboard-block",
    "analytics-dashboards-detail-block",
    "analytics-dashboards-index-block",
    "analytics-data-dictionary-block",
    "analytics-data-sources-block",
    "analytics-extensions-detail-detail-block",
    "analytics-extensions-detail-block",
    "analytics-extensions-index-block",
    "analytics-extensions-block",
    "analytics-overview-block",
    "analytics-sessions-detail-block",
    "analytics-sessions-index-block",
    "analytics-settings-block",
    "analytics-team-block",
    "analytics-traffic-dashboard-block",
    "analytics-traffic-block"
  ],
  "files": [
    {
      "path": "packages/registry/generated/workspaces/analytics.workspace.json",
      "target": "studio-ui/workspaces/analytics.workspace.json",
      "type": "registry:workspace",
      "content": "{\n  \"$schema\": \"https://jami.studio/schemas/registry/workspace-manifest.generated.json\",\n  \"name\": \"@jami-studio/analytics-workspace\",\n  \"workspace\": \"analytics\",\n  \"schemaVersion\": \"2026-06-29.agent-native-template-workspace\",\n  \"items\": [\n    \"jami-theme\",\n    \"panel\",\n    \"button\",\n    \"chart\",\n    \"agent-panel\",\n    \"analytics-app\",\n    \"analytics-catchall-page\",\n    \"analytics-home-page\",\n    \"analytics-adhoc-detail-page\",\n    \"analytics-analyses-detail-page\",\n    \"analytics-analyses-index-page\",\n    \"analytics-ask-page\",\n    \"analytics-catalog-page\",\n    \"analytics-chart-page\",\n    \"analytics-dashboard-page\",\n    \"analytics-dashboards-detail-page\",\n    \"analytics-dashboards-index-page\",\n    \"analytics-data-dictionary-page\",\n    \"analytics-data-sources-page\",\n    \"analytics-extensions-detail-detail-page\",\n    \"analytics-extensions-detail-page\",\n    \"analytics-extensions-index-page\",\n    \"analytics-extensions-page\",\n    \"analytics-overview-page\",\n    \"analytics-sessions-detail-page\",\n    \"analytics-sessions-index-page\",\n    \"analytics-settings-page\",\n    \"analytics-team-page\",\n    \"analytics-traffic-dashboard-page\",\n    \"analytics-traffic-page\",\n    \"analytics-catchall-block\",\n    \"analytics-home-block\",\n    \"analytics-adhoc-detail-block\",\n    \"analytics-analyses-detail-block\",\n    \"analytics-analyses-index-block\",\n    \"analytics-ask-block\",\n    \"analytics-catalog-block\",\n    \"analytics-chart-block\",\n    \"analytics-dashboard-block\",\n    \"analytics-dashboards-detail-block\",\n    \"analytics-dashboards-index-block\",\n    \"analytics-data-dictionary-block\",\n    \"analytics-data-sources-block\",\n    \"analytics-extensions-detail-detail-block\",\n    \"analytics-extensions-detail-block\",\n    \"analytics-extensions-index-block\",\n    \"analytics-extensions-block\",\n    \"analytics-overview-block\",\n    \"analytics-sessions-detail-block\",\n    \"analytics-sessions-index-block\",\n    \"analytics-settings-block\",\n    \"analytics-team-block\",\n    \"analytics-traffic-dashboard-block\",\n    \"analytics-traffic-block\"\n  ],\n  \"installGraph\": {\n    \"root\": \"analytics-workspace\",\n    \"dependencies\": [\n      \"jami-theme\",\n      \"panel\",\n      \"button\",\n      \"chart\",\n      \"agent-panel\",\n      \"analytics-app\",\n      \"analytics-catchall-page\",\n      \"analytics-home-page\",\n      \"analytics-adhoc-detail-page\",\n      \"analytics-analyses-detail-page\",\n      \"analytics-analyses-index-page\",\n      \"analytics-ask-page\",\n      \"analytics-catalog-page\",\n      \"analytics-chart-page\",\n      \"analytics-dashboard-page\",\n      \"analytics-dashboards-detail-page\",\n      \"analytics-dashboards-index-page\",\n      \"analytics-data-dictionary-page\",\n      \"analytics-data-sources-page\",\n      \"analytics-extensions-detail-detail-page\",\n      \"analytics-extensions-detail-page\",\n      \"analytics-extensions-index-page\",\n      \"analytics-extensions-page\",\n      \"analytics-overview-page\",\n      \"analytics-sessions-detail-page\",\n      \"analytics-sessions-index-page\",\n      \"analytics-settings-page\",\n      \"analytics-team-page\",\n      \"analytics-traffic-dashboard-page\",\n      \"analytics-traffic-page\",\n      \"analytics-catchall-block\",\n      \"analytics-home-block\",\n      \"analytics-adhoc-detail-block\",\n      \"analytics-analyses-detail-block\",\n      \"analytics-analyses-index-block\",\n      \"analytics-ask-block\",\n      \"analytics-catalog-block\",\n      \"analytics-chart-block\",\n      \"analytics-dashboard-block\",\n      \"analytics-dashboards-detail-block\",\n      \"analytics-dashboards-index-block\",\n      \"analytics-data-dictionary-block\",\n      \"analytics-data-sources-block\",\n      \"analytics-extensions-detail-detail-block\",\n      \"analytics-extensions-detail-block\",\n      \"analytics-extensions-index-block\",\n      \"analytics-extensions-block\",\n      \"analytics-overview-block\",\n      \"analytics-sessions-detail-block\",\n      \"analytics-sessions-index-block\",\n      \"analytics-settings-block\",\n      \"analytics-team-block\",\n      \"analytics-traffic-dashboard-block\",\n      \"analytics-traffic-block\"\n    ]\n  },\n  \"plannedSurfaces\": [\n    \":\",\n    \"analytics\",\n    \"adhoc\",\n    \"analyses\",\n    \"analyses\",\n    \"ask\",\n    \"catalog\",\n    \"chart\",\n    \"dashboard\",\n    \"dashboards\",\n    \"dashboards\",\n    \"data-dictionary\",\n    \"data-sources\",\n    \"extensions\",\n    \"extensions\",\n    \"extensions\",\n    \"extensions\",\n    \"overview\",\n    \"sessions\",\n    \"sessions\",\n    \"settings\",\n    \"team\",\n    \"traffic-dashboard\",\n    \"traffic\"\n  ],\n  \"shell\": {\n    \"sourceSchemaVersion\": \"2026-06-29.agent-native-template-workspace\",\n    \"title\": \"Agent-Native Analytics\",\n    \"summary\": \"Agent-Native Analytics Agent-Native template ported into Studio UI as a Harness-safe workspace surface with route inventory, provenance, resident-renderer blocks, and display-only agent/action affordances.\",\n    \"appShell\": {\n      \"id\": \"app.analytics.shell\",\n      \"layout\": \"agent-native-template-workspace\",\n      \"navigation\": [\n        {\n          \"label\": \"Catchall\",\n          \"route\": \"/analytics/:\"\n        },\n        {\n          \"label\": \"Home\",\n          \"route\": \"/analytics\"\n        },\n        {\n          \"label\": \"Adhoc Detail\",\n          \"route\": \"/analytics/adhoc/:id\"\n        },\n        {\n          \"label\": \"Analyses Detail\",\n          \"route\": \"/analytics/analyses/:id\"\n        },\n        {\n          \"label\": \"Analyses Index\",\n          \"route\": \"/analytics/analyses\"\n        },\n        {\n          \"label\": \"Ask\",\n          \"route\": \"/analytics/ask\"\n        },\n        {\n          \"label\": \"Catalog\",\n          \"route\": \"/analytics/catalog\"\n        },\n        {\n          \"label\": \"Chart\",\n          \"route\": \"/analytics/chart\"\n        }\n      ]\n    },\n    \"routes\": [\n      {\n        \"path\": \"/analytics/:\",\n        \"page\": \"page.analytics.catchall\",\n        \"title\": \"Catchall\",\n        \"blocks\": [\n          \"block.analytics.catchall\"\n        ],\n        \"sourceRouteFile\": \"agent-native/templates/analytics/app/routes/$.tsx\"\n      },\n      {\n        \"path\": \"/analytics\",\n        \"page\": \"page.analytics.home\",\n        \"title\": \"Analytics Home\",\n        \"blocks\": [\n          \"block.analytics.home\"\n        ],\n        \"sourceRouteFile\": \"agent-native/templates/analytics/app/routes/_index.tsx\"\n      },\n      {\n        \"path\": \"/analytics/adhoc/:id\",\n        \"page\": \"page.analytics.adhoc-detail\",\n        \"title\": \"Adhoc Detail\",\n        \"blocks\": [\n          \"block.analytics.adhoc-detail\"\n        ],\n        \"sourceRouteFile\": \"agent-native/templates/analytics/app/routes/adhoc.$id.tsx\"\n      },\n      {\n        \"path\": \"/analytics/analyses/:id\",\n        \"page\": \"page.analytics.analyses-detail\",\n        \"title\": \"Analyses Detail\",\n        \"blocks\": [\n          \"block.analytics.analyses-detail\"\n        ],\n        \"sourceRouteFile\": \"agent-native/templates/analytics/app/routes/analyses.$id.tsx\"\n      },\n      {\n        \"path\": \"/analytics/analyses\",\n        \"page\": \"page.analytics.analyses-index\",\n        \"title\": \"Analyses Index\",\n        \"blocks\": [\n          \"block.analytics.analyses-index\"\n        ],\n        \"sourceRouteFile\": \"agent-native/templates/analytics/app/routes/analyses._index.tsx\"\n      },\n      {\n        \"path\": \"/analytics/ask\",\n        \"page\": \"page.analytics.ask\",\n        \"title\": \"Ask\",\n        \"blocks\": [\n          \"block.analytics.ask\"\n        ],\n        \"sourceRouteFile\": \"agent-native/templates/analytics/app/routes/ask.tsx\"\n      },\n      {\n        \"path\": \"/analytics/catalog\",\n        \"page\": \"page.analytics.catalog\",\n        \"title\": \"Catalog\",\n        \"blocks\": [\n          \"block.analytics.catalog\"\n        ],\n        \"sourceRouteFile\": \"agent-native/templates/analytics/app/routes/catalog.tsx\"\n      },\n      {\n        \"path\": \"/analytics/chart\",\n        \"page\": \"page.analytics.chart\",\n        \"title\": \"Chart\",\n        \"blocks\": [\n          \"block.analytics.chart\"\n        ],\n        \"sourceRouteFile\": \"agent-native/templates/analytics/app/routes/chart.tsx\"\n      },\n      {\n        \"path\": \"/analytics/dashboard\",\n        \"page\": \"page.analytics.dashboard\",\n        \"title\": \"Dashboard\",\n        \"blocks\": [\n          \"block.analytics.dashboard\"\n        ],\n        \"sourceRouteFile\": \"agent-native/templates/analytics/app/routes/dashboard.tsx\"\n      },\n      {\n        \"path\": \"/analytics/dashboards/:id\",\n        \"page\": \"page.analytics.dashboards-detail\",\n        \"title\": \"Dashboards Detail\",\n        \"blocks\": [\n          \"block.analytics.dashboards-detail\"\n        ],\n        \"sourceRouteFile\": \"agent-native/templates/analytics/app/routes/dashboards.$id.tsx\"\n      },\n      {\n        \"path\": \"/analytics/dashboards\",\n        \"page\": \"page.analytics.dashboards-index\",\n        \"title\": \"Dashboards Index\",\n        \"blocks\": [\n          \"block.analytics.dashboards-index\"\n        ],\n        \"sourceRouteFile\": \"agent-native/templates/analytics/app/routes/dashboards._index.tsx\"\n      },\n      {\n        \"path\": \"/analytics/data-dictionary\",\n        \"page\": \"page.analytics.data-dictionary\",\n        \"title\": \"Data Dictionary\",\n        \"blocks\": [\n          \"block.analytics.data-dictionary\"\n        ],\n        \"sourceRouteFile\": \"agent-native/templates/analytics/app/routes/data-dictionary.tsx\"\n      },\n      {\n        \"path\": \"/analytics/data-sources\",\n        \"page\": \"page.analytics.data-sources\",\n        \"title\": \"Data Sources\",\n        \"blocks\": [\n          \"block.analytics.data-sources\"\n        ],\n        \"sourceRouteFile\": \"agent-native/templates/analytics/app/routes/data-sources.tsx\"\n      },\n      {\n        \"path\": \"/analytics/extensions/:id/:slug\",\n        \"page\": \"page.analytics.extensions-detail-detail\",\n        \"title\": \"Extensions Detail Detail\",\n        \"blocks\": [\n          \"block.analytics.extensions-detail-detail\"\n        ],\n        \"sourceRouteFile\": \"agent-native/templates/analytics/app/routes/extensions.$id.$slug.tsx\"\n      },\n      {\n        \"path\": \"/analytics/extensions/:id\",\n        \"page\": \"page.analytics.extensions-detail\",\n        \"title\": \"Extensions Detail\",\n        \"blocks\": [\n          \"block.analytics.extensions-detail\"\n        ],\n        \"sourceRouteFile\": \"agent-native/templates/analytics/app/routes/extensions.$id.tsx\"\n      },\n      {\n        \"path\": \"/analytics/extensions\",\n        \"page\": \"page.analytics.extensions-index\",\n        \"title\": \"Extensions Index\",\n        \"blocks\": [\n          \"block.analytics.extensions-index\"\n        ],\n        \"sourceRouteFile\": \"agent-native/templates/analytics/app/routes/extensions._index.tsx\"\n      },\n      {\n        \"path\": \"/analytics/extensions\",\n        \"page\": \"page.analytics.extensions\",\n        \"title\": \"Extensions\",\n        \"blocks\": [\n          \"block.analytics.extensions\"\n        ],\n        \"sourceRouteFile\": \"agent-native/templates/analytics/app/routes/extensions.tsx\"\n      },\n      {\n        \"path\": \"/analytics/overview\",\n        \"page\": \"page.analytics.overview\",\n        \"title\": \"Overview\",\n        \"blocks\": [\n          \"block.analytics.overview\"\n        ],\n        \"sourceRouteFile\": \"agent-native/templates/analytics/app/routes/overview.tsx\"\n      },\n      {\n        \"path\": \"/analytics/sessions/:recordingId\",\n        \"page\": \"page.analytics.sessions-detail\",\n        \"title\": \"Sessions Detail\",\n        \"blocks\": [\n          \"block.analytics.sessions-detail\"\n        ],\n        \"sourceRouteFile\": \"agent-native/templates/analytics/app/routes/sessions.$recordingId.tsx\"\n      },\n      {\n        \"path\": \"/analytics/sessions\",\n        \"page\": \"page.analytics.sessions-index\",\n        \"title\": \"Sessions Index\",\n        \"blocks\": [\n          \"block.analytics.sessions-index\"\n        ],\n        \"sourceRouteFile\": \"agent-native/templates/analytics/app/routes/sessions._index.tsx\"\n      },\n      {\n        \"path\": \"/analytics/settings\",\n        \"page\": \"page.analytics.settings\",\n        \"title\": \"Settings\",\n        \"blocks\": [\n          \"block.analytics.settings\"\n        ],\n        \"sourceRouteFile\": \"agent-native/templates/analytics/app/routes/settings.tsx\"\n      },\n      {\n        \"path\": \"/analytics/team\",\n        \"page\": \"page.analytics.team\",\n        \"title\": \"Team\",\n        \"blocks\": [\n          \"block.analytics.team\"\n        ],\n        \"sourceRouteFile\": \"agent-native/templates/analytics/app/routes/team.tsx\"\n      },\n      {\n        \"path\": \"/analytics/traffic-dashboard\",\n        \"page\": \"page.analytics.traffic-dashboard\",\n        \"title\": \"Traffic Dashboard\",\n        \"blocks\": [\n          \"block.analytics.traffic-dashboard\"\n        ],\n        \"sourceRouteFile\": \"agent-native/templates/analytics/app/routes/traffic-dashboard.tsx\"\n      },\n      {\n        \"path\": \"/analytics/traffic\",\n        \"page\": \"page.analytics.traffic\",\n        \"title\": \"Traffic\",\n        \"blocks\": [\n          \"block.analytics.traffic\"\n        ],\n        \"sourceRouteFile\": \"agent-native/templates/analytics/app/routes/traffic.tsx\"\n      }\n    ],\n    \"pages\": [\n      {\n        \"id\": \"page.analytics.catchall\",\n        \"title\": \"Catchall\",\n        \"description\": \"Agent-Native analytics route /: derived from $.tsx.\",\n        \"components\": [\n          \"chart\",\n          \"panel\",\n          \"button\"\n        ],\n        \"sourceRouteFile\": \"agent-native/templates/analytics/app/routes/$.tsx\"\n      },\n      {\n        \"id\": \"page.analytics.home\",\n        \"title\": \"Analytics Home\",\n        \"description\": \"Agent-Native analytics route / derived from _index.tsx.\",\n        \"components\": [\n          \"chart\",\n          \"panel\",\n          \"button\"\n        ],\n        \"sourceRouteFile\": \"agent-native/templates/analytics/app/routes/_index.tsx\"\n      },\n      {\n        \"id\": \"page.analytics.adhoc-detail\",\n        \"title\": \"Adhoc Detail\",\n        \"description\": \"Agent-Native analytics route /adhoc/:id derived from adhoc.$id.tsx.\",\n        \"components\": [\n          \"chart\",\n          \"panel\",\n          \"button\"\n        ],\n        \"sourceRouteFile\": \"agent-native/templates/analytics/app/routes/adhoc.$id.tsx\"\n      },\n      {\n        \"id\": \"page.analytics.analyses-detail\",\n        \"title\": \"Analyses Detail\",\n        \"description\": \"Agent-Native analytics route /analyses/:id derived from analyses.$id.tsx.\",\n        \"components\": [\n          \"chart\",\n          \"panel\",\n          \"button\"\n        ],\n        \"sourceRouteFile\": \"agent-native/templates/analytics/app/routes/analyses.$id.tsx\"\n      },\n      {\n        \"id\": \"page.analytics.analyses-index\",\n        \"title\": \"Analyses Index\",\n        \"description\": \"Agent-Native analytics route /analyses derived from analyses._index.tsx.\",\n        \"components\": [\n          \"chart\",\n          \"panel\",\n          \"button\"\n        ],\n        \"sourceRouteFile\": \"agent-native/templates/analytics/app/routes/analyses._index.tsx\"\n      },\n      {\n        \"id\": \"page.analytics.ask\",\n        \"title\": \"Ask\",\n        \"description\": \"Agent-Native analytics route /ask derived from ask.tsx.\",\n        \"components\": [\n          \"agent-panel\",\n          \"panel\",\n          \"button\"\n        ],\n        \"sourceRouteFile\": \"agent-native/templates/analytics/app/routes/ask.tsx\"\n      },\n      {\n        \"id\": \"page.analytics.catalog\",\n        \"title\": \"Catalog\",\n        \"description\": \"Agent-Native analytics route /catalog derived from catalog.tsx.\",\n        \"components\": [\n          \"chart\",\n          \"panel\",\n          \"button\"\n        ],\n        \"sourceRouteFile\": \"agent-native/templates/analytics/app/routes/catalog.tsx\"\n      },\n      {\n        \"id\": \"page.analytics.chart\",\n        \"title\": \"Chart\",\n        \"description\": \"Agent-Native analytics route /chart derived from chart.tsx.\",\n        \"components\": [\n          \"chart\",\n          \"panel\",\n          \"button\"\n        ],\n        \"sourceRouteFile\": \"agent-native/templates/analytics/app/routes/chart.tsx\"\n      },\n      {\n        \"id\": \"page.analytics.dashboard\",\n        \"title\": \"Dashboard\",\n        \"description\": \"Agent-Native analytics route /dashboard derived from dashboard.tsx.\",\n        \"components\": [\n          \"chart\",\n          \"panel\",\n          \"button\"\n        ],\n        \"sourceRouteFile\": \"agent-native/templates/analytics/app/routes/dashboard.tsx\"\n      },\n      {\n        \"id\": \"page.analytics.dashboards-detail\",\n        \"title\": \"Dashboards Detail\",\n        \"description\": \"Agent-Native analytics route /dashboards/:id derived from dashboards.$id.tsx.\",\n        \"components\": [\n          \"chart\",\n          \"panel\",\n          \"button\"\n        ],\n        \"sourceRouteFile\": \"agent-native/templates/analytics/app/routes/dashboards.$id.tsx\"\n      },\n      {\n        \"id\": \"page.analytics.dashboards-index\",\n        \"title\": \"Dashboards Index\",\n        \"description\": \"Agent-Native analytics route /dashboards derived from dashboards._index.tsx.\",\n        \"components\": [\n          \"chart\",\n          \"panel\",\n          \"button\"\n        ],\n        \"sourceRouteFile\": \"agent-native/templates/analytics/app/routes/dashboards._index.tsx\"\n      },\n      {\n        \"id\": \"page.analytics.data-dictionary\",\n        \"title\": \"Data Dictionary\",\n        \"description\": \"Agent-Native analytics route /data-dictionary derived from data-dictionary.tsx.\",\n        \"components\": [\n          \"chart\",\n          \"panel\",\n          \"button\"\n        ],\n        \"sourceRouteFile\": \"agent-native/templates/analytics/app/routes/data-dictionary.tsx\"\n      },\n      {\n        \"id\": \"page.analytics.data-sources\",\n        \"title\": \"Data Sources\",\n        \"description\": \"Agent-Native analytics route /data-sources derived from data-sources.tsx.\",\n        \"components\": [\n          \"chart\",\n          \"panel\",\n          \"button\"\n        ],\n        \"sourceRouteFile\": \"agent-native/templates/analytics/app/routes/data-sources.tsx\"\n      },\n      {\n        \"id\": \"page.analytics.extensions-detail-detail\",\n        \"title\": \"Extensions Detail Detail\",\n        \"description\": \"Agent-Native analytics route /extensions/:id/:slug derived from extensions.$id.$slug.tsx.\",\n        \"components\": [\n          \"chart\",\n          \"panel\",\n          \"button\"\n        ],\n        \"sourceRouteFile\": \"agent-native/templates/analytics/app/routes/extensions.$id.$slug.tsx\"\n      },\n      {\n        \"id\": \"page.analytics.extensions-detail\",\n        \"title\": \"Extensions Detail\",\n        \"description\": \"Agent-Native analytics route /extensions/:id derived from extensions.$id.tsx.\",\n        \"components\": [\n          \"chart\",\n          \"panel\",\n          \"button\"\n        ],\n        \"sourceRouteFile\": \"agent-native/templates/analytics/app/routes/extensions.$id.tsx\"\n      },\n      {\n        \"id\": \"page.analytics.extensions-index\",\n        \"title\": \"Extensions Index\",\n        \"description\": \"Agent-Native analytics route /extensions derived from extensions._index.tsx.\",\n        \"components\": [\n          \"chart\",\n          \"panel\",\n          \"button\"\n        ],\n        \"sourceRouteFile\": \"agent-native/templates/analytics/app/routes/extensions._index.tsx\"\n      },\n      {\n        \"id\": \"page.analytics.extensions\",\n        \"title\": \"Extensions\",\n        \"description\": \"Agent-Native analytics route /extensions derived from extensions.tsx.\",\n        \"components\": [\n          \"chart\",\n          \"panel\",\n          \"button\"\n        ],\n        \"sourceRouteFile\": \"agent-native/templates/analytics/app/routes/extensions.tsx\"\n      },\n      {\n        \"id\": \"page.analytics.overview\",\n        \"title\": \"Overview\",\n        \"description\": \"Agent-Native analytics route /overview derived from overview.tsx.\",\n        \"components\": [\n          \"chart\",\n          \"panel\",\n          \"button\"\n        ],\n        \"sourceRouteFile\": \"agent-native/templates/analytics/app/routes/overview.tsx\"\n      },\n      {\n        \"id\": \"page.analytics.sessions-detail\",\n        \"title\": \"Sessions Detail\",\n        \"description\": \"Agent-Native analytics route /sessions/:recordingId derived from sessions.$recordingId.tsx.\",\n        \"components\": [\n          \"chart\",\n          \"panel\",\n          \"button\"\n        ],\n        \"sourceRouteFile\": \"agent-native/templates/analytics/app/routes/sessions.$recordingId.tsx\"\n      },\n      {\n        \"id\": \"page.analytics.sessions-index\",\n        \"title\": \"Sessions Index\",\n        \"description\": \"Agent-Native analytics route /sessions derived from sessions._index.tsx.\",\n        \"components\": [\n          \"chart\",\n          \"panel\",\n          \"button\"\n        ],\n        \"sourceRouteFile\": \"agent-native/templates/analytics/app/routes/sessions._index.tsx\"\n      },\n      {\n        \"id\": \"page.analytics.settings\",\n        \"title\": \"Settings\",\n        \"description\": \"Agent-Native analytics route /settings derived from settings.tsx.\",\n        \"components\": [\n          \"chart\",\n          \"panel\",\n          \"button\"\n        ],\n        \"sourceRouteFile\": \"agent-native/templates/analytics/app/routes/settings.tsx\"\n      },\n      {\n        \"id\": \"page.analytics.team\",\n        \"title\": \"Team\",\n        \"description\": \"Agent-Native analytics route /team derived from team.tsx.\",\n        \"components\": [\n          \"chart\",\n          \"panel\",\n          \"button\"\n        ],\n        \"sourceRouteFile\": \"agent-native/templates/analytics/app/routes/team.tsx\"\n      },\n      {\n        \"id\": \"page.analytics.traffic-dashboard\",\n        \"title\": \"Traffic Dashboard\",\n        \"description\": \"Agent-Native analytics route /traffic-dashboard derived from traffic-dashboard.tsx.\",\n        \"components\": [\n          \"chart\",\n          \"panel\",\n          \"button\"\n        ],\n        \"sourceRouteFile\": \"agent-native/templates/analytics/app/routes/traffic-dashboard.tsx\"\n      },\n      {\n        \"id\": \"page.analytics.traffic\",\n        \"title\": \"Traffic\",\n        \"description\": \"Agent-Native analytics route /traffic derived from traffic.tsx.\",\n        \"components\": [\n          \"chart\",\n          \"panel\",\n          \"button\"\n        ],\n        \"sourceRouteFile\": \"agent-native/templates/analytics/app/routes/traffic.tsx\"\n      }\n    ],\n    \"blocks\": [\n      {\n        \"id\": \"block.analytics.catchall\",\n        \"title\": \"Catchall\",\n        \"component\": \"chart\",\n        \"stateExamples\": [\n          \"loading\",\n          \"empty\",\n          \"error\",\n          \"long-content\"\n        ],\n        \"sourceRouteFile\": \"agent-native/templates/analytics/app/routes/$.tsx\"\n      },\n      {\n        \"id\": \"block.analytics.home\",\n        \"title\": \"Home\",\n        \"component\": \"chart\",\n        \"stateExamples\": [\n          \"loading\",\n          \"empty\",\n          \"error\",\n          \"long-content\"\n        ],\n        \"sourceRouteFile\": \"agent-native/templates/analytics/app/routes/_index.tsx\"\n      },\n      {\n        \"id\": \"block.analytics.adhoc-detail\",\n        \"title\": \"Adhoc Detail\",\n        \"component\": \"chart\",\n        \"stateExamples\": [\n          \"loading\",\n          \"empty\",\n          \"error\",\n          \"long-content\"\n        ],\n        \"sourceRouteFile\": \"agent-native/templates/analytics/app/routes/adhoc.$id.tsx\"\n      },\n      {\n        \"id\": \"block.analytics.analyses-detail\",\n        \"title\": \"Analyses Detail\",\n        \"component\": \"chart\",\n        \"stateExamples\": [\n          \"loading\",\n          \"empty\",\n          \"error\",\n          \"long-content\"\n        ],\n        \"sourceRouteFile\": \"agent-native/templates/analytics/app/routes/analyses.$id.tsx\"\n      },\n      {\n        \"id\": \"block.analytics.analyses-index\",\n        \"title\": \"Analyses Index\",\n        \"component\": \"chart\",\n        \"stateExamples\": [\n          \"loading\",\n          \"empty\",\n          \"error\",\n          \"long-content\"\n        ],\n        \"sourceRouteFile\": \"agent-native/templates/analytics/app/routes/analyses._index.tsx\"\n      },\n      {\n        \"id\": \"block.analytics.ask\",\n        \"title\": \"Ask\",\n        \"component\": \"agent-panel\",\n        \"stateExamples\": [\n          \"loading\",\n          \"empty\",\n          \"error\"\n        ],\n        \"sourceRouteFile\": \"agent-native/templates/analytics/app/routes/ask.tsx\"\n      },\n      {\n        \"id\": \"block.analytics.catalog\",\n        \"title\": \"Catalog\",\n        \"component\": \"chart\",\n        \"stateExamples\": [\n          \"loading\",\n          \"empty\",\n          \"error\",\n          \"long-content\"\n        ],\n        \"sourceRouteFile\": \"agent-native/templates/analytics/app/routes/catalog.tsx\"\n      },\n      {\n        \"id\": \"block.analytics.chart\",\n        \"title\": \"Chart\",\n        \"component\": \"chart\",\n        \"stateExamples\": [\n          \"loading\",\n          \"empty\",\n          \"error\",\n          \"long-content\"\n        ],\n        \"sourceRouteFile\": \"agent-native/templates/analytics/app/routes/chart.tsx\"\n      },\n      {\n        \"id\": \"block.analytics.dashboard\",\n        \"title\": \"Dashboard\",\n        \"component\": \"chart\",\n        \"stateExamples\": [\n          \"loading\",\n          \"empty\",\n          \"error\",\n          \"long-content\"\n        ],\n        \"sourceRouteFile\": \"agent-native/templates/analytics/app/routes/dashboard.tsx\"\n      },\n      {\n        \"id\": \"block.analytics.dashboards-detail\",\n        \"title\": \"Dashboards Detail\",\n        \"component\": \"chart\",\n        \"stateExamples\": [\n          \"loading\",\n          \"empty\",\n          \"error\",\n          \"long-content\"\n        ],\n        \"sourceRouteFile\": \"agent-native/templates/analytics/app/routes/dashboards.$id.tsx\"\n      },\n      {\n        \"id\": \"block.analytics.dashboards-index\",\n        \"title\": \"Dashboards Index\",\n        \"component\": \"chart\",\n        \"stateExamples\": [\n          \"loading\",\n          \"empty\",\n          \"error\",\n          \"long-content\"\n        ],\n        \"sourceRouteFile\": \"agent-native/templates/analytics/app/routes/dashboards._index.tsx\"\n      },\n      {\n        \"id\": \"block.analytics.data-dictionary\",\n        \"title\": \"Data Dictionary\",\n        \"component\": \"chart\",\n        \"stateExamples\": [\n          \"loading\",\n          \"empty\",\n          \"error\",\n          \"long-content\"\n        ],\n        \"sourceRouteFile\": \"agent-native/templates/analytics/app/routes/data-dictionary.tsx\"\n      },\n      {\n        \"id\": \"block.analytics.data-sources\",\n        \"title\": \"Data Sources\",\n        \"component\": \"chart\",\n        \"stateExamples\": [\n          \"loading\",\n          \"empty\",\n          \"error\",\n          \"long-content\"\n        ],\n        \"sourceRouteFile\": \"agent-native/templates/analytics/app/routes/data-sources.tsx\"\n      },\n      {\n        \"id\": \"block.analytics.extensions-detail-detail\",\n        \"title\": \"Extensions Detail Detail\",\n        \"component\": \"chart\",\n        \"stateExamples\": [\n          \"loading\",\n          \"empty\",\n          \"error\",\n          \"long-content\"\n        ],\n        \"sourceRouteFile\": \"agent-native/templates/analytics/app/routes/extensions.$id.$slug.tsx\"\n      },\n      {\n        \"id\": \"block.analytics.extensions-detail\",\n        \"title\": \"Extensions Detail\",\n        \"component\": \"chart\",\n        \"stateExamples\": [\n          \"loading\",\n          \"empty\",\n          \"error\",\n          \"long-content\"\n        ],\n        \"sourceRouteFile\": \"agent-native/templates/analytics/app/routes/extensions.$id.tsx\"\n      },\n      {\n        \"id\": \"block.analytics.extensions-index\",\n        \"title\": \"Extensions Index\",\n        \"component\": \"chart\",\n        \"stateExamples\": [\n          \"loading\",\n          \"empty\",\n          \"error\",\n          \"long-content\"\n        ],\n        \"sourceRouteFile\": \"agent-native/templates/analytics/app/routes/extensions._index.tsx\"\n      },\n      {\n        \"id\": \"block.analytics.extensions\",\n        \"title\": \"Extensions\",\n        \"component\": \"chart\",\n        \"stateExamples\": [\n          \"loading\",\n          \"empty\",\n          \"error\",\n          \"long-content\"\n        ],\n        \"sourceRouteFile\": \"agent-native/templates/analytics/app/routes/extensions.tsx\"\n      },\n      {\n        \"id\": \"block.analytics.overview\",\n        \"title\": \"Overview\",\n        \"component\": \"chart\",\n        \"stateExamples\": [\n          \"loading\",\n          \"empty\",\n          \"error\",\n          \"long-content\"\n        ],\n        \"sourceRouteFile\": \"agent-native/templates/analytics/app/routes/overview.tsx\"\n      },\n      {\n        \"id\": \"block.analytics.sessions-detail\",\n        \"title\": \"Sessions Detail\",\n        \"component\": \"chart\",\n        \"stateExamples\": [\n          \"loading\",\n          \"empty\",\n          \"error\",\n          \"long-content\"\n        ],\n        \"sourceRouteFile\": \"agent-native/templates/analytics/app/routes/sessions.$recordingId.tsx\"\n      },\n      {\n        \"id\": \"block.analytics.sessions-index\",\n        \"title\": \"Sessions Index\",\n        \"component\": \"chart\",\n        \"stateExamples\": [\n          \"loading\",\n          \"empty\",\n          \"error\",\n          \"long-content\"\n        ],\n        \"sourceRouteFile\": \"agent-native/templates/analytics/app/routes/sessions._index.tsx\"\n      },\n      {\n        \"id\": \"block.analytics.settings\",\n        \"title\": \"Settings\",\n        \"component\": \"chart\",\n        \"stateExamples\": [\n          \"loading\",\n          \"empty\",\n          \"error\",\n          \"long-content\"\n        ],\n        \"sourceRouteFile\": \"agent-native/templates/analytics/app/routes/settings.tsx\"\n      },\n      {\n        \"id\": \"block.analytics.team\",\n        \"title\": \"Team\",\n        \"component\": \"chart\",\n        \"stateExamples\": [\n          \"loading\",\n          \"empty\",\n          \"error\",\n          \"long-content\"\n        ],\n        \"sourceRouteFile\": \"agent-native/templates/analytics/app/routes/team.tsx\"\n      },\n      {\n        \"id\": \"block.analytics.traffic-dashboard\",\n        \"title\": \"Traffic Dashboard\",\n        \"component\": \"chart\",\n        \"stateExamples\": [\n          \"loading\",\n          \"empty\",\n          \"error\",\n          \"long-content\"\n        ],\n        \"sourceRouteFile\": \"agent-native/templates/analytics/app/routes/traffic-dashboard.tsx\"\n      },\n      {\n        \"id\": \"block.analytics.traffic\",\n        \"title\": \"Traffic\",\n        \"component\": \"chart\",\n        \"stateExamples\": [\n          \"loading\",\n          \"empty\",\n          \"error\",\n          \"long-content\"\n        ],\n        \"sourceRouteFile\": \"agent-native/templates/analytics/app/routes/traffic.tsx\"\n      }\n    ],\n    \"componentParts\": [\n      \"agent-panel\",\n      \"button\",\n      \"chart\",\n      \"panel\"\n    ],\n    \"stateFixtures\": {\n      \"longContent\": \"Agent-Native Analytics keeps the original Agent-Native route inventory visible while Studio UI renders safe resident components for Harness inspection.\",\n      \"empty\": \"No records are loaded for Agent-Native Analytics in the local Studio UI port; the original Agent-Native data/runtime remains referenced by source path.\",\n      \"error\": \"Agent-Native Analytics agent or action state is display-only until Jami Harness owns the runtime execution path.\"\n    },\n    \"agentNativeTemplate\": {\n      \"sourceRepo\": \"https://github.com/yrka-io/agent-native.git\",\n      \"upstreamRepo\": \"https://github.com/BuilderIO/agent-native.git\",\n      \"sourcePath\": \"agent-native/templates/analytics\",\n      \"copiedSource\": false,\n      \"license\": \"ISC\",\n      \"importedAs\": \"jami-authored workspace shell and registry metadata derived from Agent-Native template structure\",\n      \"sourceDirectories\": [\n        \"actions\",\n        \"app\",\n        \"server\",\n        \"shared\",\n        \"data\",\n        \"public\"\n      ]\n    },\n    \"provenance\": {\n      \"source\": \"registry/workspaces/analytics/workspace-shell.json\",\n      \"copiedSource\": false\n    }\n  },\n  \"implementation\": {\n    \"status\": \"mounted-react-workspace-implementation\",\n    \"runtimeReactApp\": true,\n    \"hostedRuntime\": false,\n    \"source\": \"packages/ui/src/workspaces.mjs\",\n    \"app\": \"studio-ui/workspaces/analytics/analytics-app.implementation.json\",\n    \"pages\": [\n      \"studio-ui/workspaces/analytics/pages/analytics-catchall-page.page.implementation.json\",\n      \"studio-ui/workspaces/analytics/pages/analytics-home-page.page.implementation.json\",\n      \"studio-ui/workspaces/analytics/pages/analytics-adhoc-detail-page.page.implementation.json\",\n      \"studio-ui/workspaces/analytics/pages/analytics-analyses-detail-page.page.implementation.json\",\n      \"studio-ui/workspaces/analytics/pages/analytics-analyses-index-page.page.implementation.json\",\n      \"studio-ui/workspaces/analytics/pages/analytics-ask-page.page.implementation.json\",\n      \"studio-ui/workspaces/analytics/pages/analytics-catalog-page.page.implementation.json\",\n      \"studio-ui/workspaces/analytics/pages/analytics-chart-page.page.implementation.json\",\n      \"studio-ui/workspaces/analytics/pages/analytics-dashboard-page.page.implementation.json\",\n      \"studio-ui/workspaces/analytics/pages/analytics-dashboards-detail-page.page.implementation.json\",\n      \"studio-ui/workspaces/analytics/pages/analytics-dashboards-index-page.page.implementation.json\",\n      \"studio-ui/workspaces/analytics/pages/analytics-data-dictionary-page.page.implementation.json\",\n      \"studio-ui/workspaces/analytics/pages/analytics-data-sources-page.page.implementation.json\",\n      \"studio-ui/workspaces/analytics/pages/analytics-extensions-detail-detail-page.page.implementation.json\",\n      \"studio-ui/workspaces/analytics/pages/analytics-extensions-detail-page.page.implementation.json\",\n      \"studio-ui/workspaces/analytics/pages/analytics-extensions-index-page.page.implementation.json\",\n      \"studio-ui/workspaces/analytics/pages/analytics-extensions-page.page.implementation.json\",\n      \"studio-ui/workspaces/analytics/pages/analytics-overview-page.page.implementation.json\",\n      \"studio-ui/workspaces/analytics/pages/analytics-sessions-detail-page.page.implementation.json\",\n      \"studio-ui/workspaces/analytics/pages/analytics-sessions-index-page.page.implementation.json\",\n      \"studio-ui/workspaces/analytics/pages/analytics-settings-page.page.implementation.json\",\n      \"studio-ui/workspaces/analytics/pages/analytics-team-page.page.implementation.json\",\n      \"studio-ui/workspaces/analytics/pages/analytics-traffic-dashboard-page.page.implementation.json\",\n      \"studio-ui/workspaces/analytics/pages/analytics-traffic-page.page.implementation.json\"\n    ],\n    \"blocks\": [\n      \"studio-ui/workspaces/analytics/blocks/analytics-catchall-block.block.implementation.json\",\n      \"studio-ui/workspaces/analytics/blocks/analytics-home-block.block.implementation.json\",\n      \"studio-ui/workspaces/analytics/blocks/analytics-adhoc-detail-block.block.implementation.json\",\n      \"studio-ui/workspaces/analytics/blocks/analytics-analyses-detail-block.block.implementation.json\",\n      \"studio-ui/workspaces/analytics/blocks/analytics-analyses-index-block.block.implementation.json\",\n      \"studio-ui/workspaces/analytics/blocks/analytics-ask-block.block.implementation.json\",\n      \"studio-ui/workspaces/analytics/blocks/analytics-catalog-block.block.implementation.json\",\n      \"studio-ui/workspaces/analytics/blocks/analytics-chart-block.block.implementation.json\",\n      \"studio-ui/workspaces/analytics/blocks/analytics-dashboard-block.block.implementation.json\",\n      \"studio-ui/workspaces/analytics/blocks/analytics-dashboards-detail-block.block.implementation.json\",\n      \"studio-ui/workspaces/analytics/blocks/analytics-dashboards-index-block.block.implementation.json\",\n      \"studio-ui/workspaces/analytics/blocks/analytics-data-dictionary-block.block.implementation.json\",\n      \"studio-ui/workspaces/analytics/blocks/analytics-data-sources-block.block.implementation.json\",\n      \"studio-ui/workspaces/analytics/blocks/analytics-extensions-detail-detail-block.block.implementation.json\",\n      \"studio-ui/workspaces/analytics/blocks/analytics-extensions-detail-block.block.implementation.json\",\n      \"studio-ui/workspaces/analytics/blocks/analytics-extensions-index-block.block.implementation.json\",\n      \"studio-ui/workspaces/analytics/blocks/analytics-extensions-block.block.implementation.json\",\n      \"studio-ui/workspaces/analytics/blocks/analytics-overview-block.block.implementation.json\",\n      \"studio-ui/workspaces/analytics/blocks/analytics-sessions-detail-block.block.implementation.json\",\n      \"studio-ui/workspaces/analytics/blocks/analytics-sessions-index-block.block.implementation.json\",\n      \"studio-ui/workspaces/analytics/blocks/analytics-settings-block.block.implementation.json\",\n      \"studio-ui/workspaces/analytics/blocks/analytics-team-block.block.implementation.json\",\n      \"studio-ui/workspaces/analytics/blocks/analytics-traffic-dashboard-block.block.implementation.json\",\n      \"studio-ui/workspaces/analytics/blocks/analytics-traffic-block.block.implementation.json\"\n    ]\n  }\n}\n",
      "hash": "sha256:ff190a9abfeba9aa3dc349e87dbf8043b7e9582ffd218d910976d680390eea38"
    }
  ],
  "meta": {
    "packageName": "@jami-studio/analytics-workspace",
    "workspace": "analytics",
    "lifecycle": {
      "id": "workspace.analytics",
      "version": "0.0.0-agent-native.20260629",
      "schemaVersion": "2026-06-29.agent-native-template-workspace",
      "sourceHash": "sha256:504aaa5fa896399ccc9dc7ed5ee8a8d35e6fca5eb937d2d684af6144b8d4b644",
      "migrationNotes": "Agent-Native Agent-Native Analytics template imported from yrka-io/agent-native as a complete Studio UI workspace shell over all discovered route files; execution remains display-only behind Jami Harness contracts."
    },
    "tokenRequirements": [
      "semantic.light.background",
      "semantic.light.surface",
      "semantic.light.foreground",
      "semantic.light.accent",
      "semantic.light.border",
      "componentState.focusRing"
    ],
    "provenance": {
      "source": "agent-native/templates/analytics",
      "license": "ISC",
      "reviewedAt": "2026-06-29",
      "copiedSource": false,
      "upstream": {
        "sourceRepo": "https://github.com/yrka-io/agent-native.git",
        "upstreamRepo": "https://github.com/BuilderIO/agent-native.git",
        "sourcePath": "agent-native/templates/analytics",
        "copiedSource": false,
        "license": "ISC",
        "importedAs": "jami-authored workspace shell and registry metadata derived from Agent-Native template structure",
        "sourceDirectories": [
          "actions",
          "app",
          "server",
          "shared",
          "data",
          "public"
        ]
      },
      "sourceHash": "sha256:92acae1baf9c214857b9e31a78a5f2c1c5f73d8217be1bca8041d3d90b195523"
    },
    "compatibility": {
      "shadcn": "Studio UI registry metadata generated from Agent-Native template route inventory; source app remains upstream-owned until forked into Jami packages.",
      "tailwind": "Consumes generated --jami-* CSS variables in the Studio UI workbench port.",
      "react": "19.2.7"
    },
    "plannedSurfaces": [
      ":",
      "analytics",
      "adhoc",
      "analyses",
      "analyses",
      "ask",
      "catalog",
      "chart",
      "dashboard",
      "dashboards",
      "dashboards",
      "data-dictionary",
      "data-sources",
      "extensions",
      "extensions",
      "extensions",
      "extensions",
      "overview",
      "sessions",
      "sessions",
      "settings",
      "team",
      "traffic-dashboard",
      "traffic"
    ],
    "agentManifest": null
  }
}
